galaxy_updater/__init__.py
galaxy_updater/galaxy_updater.py
galaxy_updater-0.4.0.dist-info/DESCRIPTION.rst
galaxy_updater-0.4.0.dist-info/METADATA
galaxy_updater-0.4.0.dist-info/RECORD
galaxy_updater-0.4.0.dist-info/WHEEL
galaxy_updater-0.4.0.dist-info/entry_points.txt
galaxy_updater-0.4.0.dist-info/metadata.json
galaxy_updater-0.4.0.dist-info/top_level.txt
