Metadata-Version: 2.0
Name: galaxy-updater
Version: 0.4.0
Summary: Retrieve the latest versions for all of your ansible-galaxy role dependencies.
Home-page: https://github.com/danrue/galaxy_updater
Author: Dan Rue
Author-email: drue@therub.org
License: BSD
Keywords: ansible-galaxy ansible galaxy requirements.yml
Platform: UNKNOWN
Classifier: Development Status :: 3 - Alpha
Classifier: Intended Audience :: Developers
Classifier: License :: OSI Approved :: BSD License
Classifier: Natural Language :: English
Classifier: Programming Language :: Python :: 2
Classifier: Programming Language :: Python :: 2.6
Classifier: Programming Language :: Python :: 2.7
Classifier: Programming Language :: Python :: 3
Classifier: Programming Language :: Python :: 3.3
Classifier: Programming Language :: Python :: 3.4
Classifier: Programming Language :: Python :: 3.5
Requires-Dist: future
Requires-Dist: requests
Requires-Dist: ruamel.yaml (==0.11.15)
